control_center/__init__.py
control_center/admin.py
control_center/base_settings.py
control_center/urls.py
control_center/wsgi.py
control_center/apps/__init__.py
control_center/apps/api/__init__.py
control_center/apps/api/serializers.py
control_center/apps/api/urls.py
control_center/apps/api/views.py
control_center/apps/compose_ui/__init__.py
control_center/apps/compose_ui/context.py
control_center/apps/compose_ui/decorators.py
control_center/apps/compose_ui/urls.py
control_center/apps/compose_ui/views.py
control_center/apps/compose_ui/static/compose_ui/compose_ui.js
control_center/apps/compose_ui/static/compose_ui/favicon.ico
control_center/apps/compose_ui/static/compose_ui/font-awesome.css
control_center/apps/compose_ui/static/compose_ui/style.css
control_center/apps/compose_ui/static/compose_ui/webfonts/fa-brands-400.eot
control_center/apps/compose_ui/static/compose_ui/webfonts/fa-brands-400.svg
control_center/apps/compose_ui/static/compose_ui/webfonts/fa-brands-400.ttf
control_center/apps/compose_ui/static/compose_ui/webfonts/fa-brands-400.woff
control_center/apps/compose_ui/static/compose_ui/webfonts/fa-brands-400.woff2
control_center/apps/compose_ui/static/compose_ui/webfonts/fa-regular-400.eot
control_center/apps/compose_ui/static/compose_ui/webfonts/fa-regular-400.svg
control_center/apps/compose_ui/static/compose_ui/webfonts/fa-regular-400.ttf
control_center/apps/compose_ui/static/compose_ui/webfonts/fa-regular-400.woff
control_center/apps/compose_ui/static/compose_ui/webfonts/fa-regular-400.woff2
control_center/apps/compose_ui/static/compose_ui/webfonts/fa-solid-900.eot
control_center/apps/compose_ui/static/compose_ui/webfonts/fa-solid-900.svg
control_center/apps/compose_ui/static/compose_ui/webfonts/fa-solid-900.ttf
control_center/apps/compose_ui/static/compose_ui/webfonts/fa-solid-900.woff
control_center/apps/compose_ui/static/compose_ui/webfonts/fa-solid-900.woff2
control_center/apps/compose_ui/templates/compose_ui/base.html
docker_compose_control_center-5.0.0.dist-info/licenses/LICENSE.md
docker_compose_control_center-5.0.0.dist-info/METADATA
docker_compose_control_center-5.0.0.dist-info/WHEEL
docker_compose_control_center-5.0.0.dist-info/top_level.txt
docker_compose_control_center-5.0.0.dist-info/RECORD
