Metadata-Version: 2.4
Name: docker_compose_control_center
Version: 5.0.0
Summary: Docker Compose Control Center is a small utility web application. It allows for control of docker containers, and specifically services created with docker-compose
Home-page: https://github.com/usnistgov/docker-control-center
Author: Center for Nanoscale Science and Technology
Author-email: CNSTapplications@nist.gov
License: Public domain
Classifier: Development Status :: 5 - Production/Stable
Classifier: Environment :: Web Environment
Classifier: Framework :: Django
Classifier: Intended Audience :: System Administrators
Classifier: Intended Audience :: Information Technology
Classifier: Intended Audience :: Developers
Classifier: License :: Public Domain
Classifier: Natural Language :: English
Classifier: Operating System :: OS Independent
Classifier: Programming Language :: Python :: 3.14
Requires-Python: >=3.14
License-File: LICENSE.md
Requires-Dist: docker==7.1.0
Requires-Dist: django==6.0
Requires-Dist: PyYAML==6.0.3
Requires-Dist: whitenoise==6.11.0
Requires-Dist: requests==2.32.5
Requires-Dist: ldap3==2.9.1
Requires-Dist: pytz==2025.2
Requires-Dist: python-dateutil==2.8.2
Requires-Dist: djangorestframework==3.16.1
Dynamic: author
Dynamic: author-email
Dynamic: classifier
Dynamic: description
Dynamic: home-page
Dynamic: license
Dynamic: license-file
Dynamic: requires-dist
Dynamic: requires-python
Dynamic: summary
